sonnen_api_v2/__init__.py
sonnen_api_v2/const.py
sonnen_api_v2/sonnen.py
sonnen_api_v2/wrapped.py
tests/__init__.py
tests/battery_charging_asyncio.py
tests/battery_charging_coroutine.py
tests/battery_charging_sync.py
tests/battery_discharging_asyncio.py
tests/battery_discharging_coroutine.py
tests/battery_discharging_reserve_asyncio.py
tests/battery_discharging_reserve_coroutine.py
tests/battery_discharging_reserve_sync.py
tests/battery_discharging_sync.py
tests/check_results.py
tests/mock_batterieresponse.py
tests/mock_battery_responses.py
tests/mock_sonnenbatterie_v2_charging.py
tests/mock_sonnenbatterie_v2_discharging.py
tests/mock_sonnenbatterie_v2_discharging_offgrid.py
tests/mock_sonnenbatterie_v2_discharging_reserve.py
tests/test_batterie.py
tests/test_batterie_charge_sync.py
tests/test_batterie_discharge_sync.py
tests/test_batterie_reserve_sync.py
tests/test_batterieresponse.py
tests/test_live_batterieresponse.py
tests/test_mock_batterie_reserve.py
tests/test_mock_batterie_wrapped.py
tests/test_sonnen.py
sonnen_api_v2-0.5.14.dist-info/LICENSE
sonnen_api_v2-0.5.14.dist-info/METADATA
sonnen_api_v2-0.5.14.dist-info/WHEEL
sonnen_api_v2-0.5.14.dist-info/top_level.txt
sonnen_api_v2-0.5.14.dist-info/RECORD
