Metadata-Version: 2.2
Name: sonnen_api_v2
Version: 0.5.14
Summary: # Sonnen API v2 package
Home-page: https://github.com/Katamave/sonnen_api_v2.git
Author: Vaclav Silhan
Author-email: katamave@gmail.com
License: MIT License
Requires-Python: >=3.12
License-File: LICENSE
Requires-Dist: requests~=2.32.3
Requires-Dist: aiohttp>=3.11.11
Requires-Dist: isal~=1.7.1
Requires-Dist: aiohttp-fast-zlib<4.0.0,>=0.2.0
Requires-Dist: urllib3<2.0.0,>=1.26.20
Requires-Dist: yarl~=1.18.3
Requires-Dist: setuptools~=75.7.0
Requires-Dist: propcache~=0.2.1
Requires-Dist: attrs~=24.2.0
Requires-Dist: pytest-asyncio~=0.24.0
Dynamic: author
Dynamic: author-email
Dynamic: home-page
Dynamic: license
Dynamic: requires-dist
Dynamic: requires-python
Dynamic: summary
